atckit/__init__.py
atckit/files.py
atckit/service.py
atckit/signals.py
atckit/subscriber.py
atckit/version.py
atckit-2.0.1.dist-info/licenses/LICENSE.md
atckit-2.0.1.dist-info/METADATA
atckit-2.0.1.dist-info/WHEEL
atckit-2.0.1.dist-info/top_level.txt
atckit-2.0.1.dist-info/RECORD
