Metadata-Version: 2.4
Name: atckit
Version: 2.0.1
Summary: AccidentallyTheCables Utility Kit
Author-email: AccidentallyTheCable <cableninja@cableninja.net>
License: GPLv3
Project-URL: Homepage, https://gitlab.com/accidentallythecable-public/python-modules/python-atckit/
Project-URL: Bug Tracker, https://gitlab.com/accidentallythecable-public/python-modules/python-atckit/issues
Classifier: Programming Language :: Python :: 3
Classifier: License :: OSI Approved :: GNU General Public License v3 (GPLv3)
Classifier: Operating System :: OS Independent
Classifier: Topic :: Utilities
Requires-Python: >=3.11
License-File: LICENSE.md
Requires-Dist: tomlkit<=0.13.0,>=0.12.0
Requires-Dist: PyYAML<=6.1.0,>=6.0.0
Requires-Dist: typing_extensions<=5.0.0,>=4.0.0
Dynamic: license-file
